be/__init__.py
be/api/__init__.py
be/api/storage.py
be/api/storage_client.py
app.json
avyas_aurica_base_apps_drive-3.1.0.dist-info/METADATA
avyas_aurica_base_apps_drive-3.1.0.dist-info/WHEEL
avyas_aurica_base_apps_drive-3.1.0.dist-info/RECORD
