Metadata-Version: 2.4
Name: avyas-aurica-base-apps-drive
Version: 3.1.0
Summary: Aurica app: drive
Requires-Python: >=3.11
Requires-Dist: fastapi>=0.104.0
Requires-Dist: uvicorn>=0.24.0
